format_print/Rehuman.py
format_print/Respacing.py
format_print/Rows_print.py
format_print/Unicode_len.py
format_print/__init__.py
format_print-1.0.dist-info/LICENSE
format_print-1.0.dist-info/METADATA
format_print-1.0.dist-info/NOTICE
format_print-1.0.dist-info/WHEEL
format_print-1.0.dist-info/top_level.txt
format_print-1.0.dist-info/RECORD
