Metadata-Version: 2.1
Name: format-print
Version: 1.0
Summary: 一个用于格式化输出的库，主要功能包括多行输出刷新、全半角字符混合对齐、秒数及字节大小格式化等
Home-page: https://github.com/taikoooo/format_print
Author: taikooo
Author-email: bbstufo@gmail.com
License: UNKNOWN
Platform: UNKNOWN
Classifier: Programming Language :: Python :: 3
Classifier: License :: OSI Approved :: Apache Software License
Classifier: Operating System :: OS Independent
Requires-Python: >=3.8
